{"cameraMode":{"drawMode":0,"name":"Shaded","section":"Shading Mode"},"sceneLighting":true,"audioPlay":false,"sceneViewState":{"m_AlwaysRefresh":false,"showFog":true,"showSkybox":true,"showFlares":true,"showImageEffects":true,"showParticleSystems":true,"showVisualEffectGraphs":true,"m_FxEnabled":true},"in2DMode":false,"pivot":{"x":753.57373046875,"y":-3603.23974609375,"z":2804.1376953125},"rotation":{"x":-0.599488377571106,"y":0.0009696697816252708,"z":-0.0007447848911397159,"w":-0.8003236055374146},"size":2815.113037109375,"orthographic":false}